autohint/__init__.py
autohint/suggestion.py
autohint-1.1.0.dist-info/METADATA
autohint-1.1.0.dist-info/WHEEL
autohint-1.1.0.dist-info/top_level.txt
autohint-1.1.0.dist-info/RECORD
