Metadata-Version: 2.1
Name: autohint
Version: 1.1.0
Summary: AutoHint provides real-time search suggestions with internet integration.
Home-page: https://github.com/Jkdevlopments/autohint
Author: Jai Akash
Author-email: akdevelopments007@gmail.com
Classifier: Programming Language :: Python :: 3
Classifier: License :: OSI Approved :: MIT License
Classifier: Operating System :: OS Independent
Requires-Python: >=3.6
Requires-Dist: prompt-toolkit
Requires-Dist: requests
Requires-Dist: bs4
